setup.cfg
setup.py
pysterior/__init__.py
pysterior/classification.py
pysterior/data_util.py
pysterior/demos.py
pysterior/regression.py
pysterior.egg-info/PKG-INFO
pysterior.egg-info/SOURCES.txt
pysterior.egg-info/dependency_links.txt
pysterior.egg-info/requires.txt
pysterior.egg-info/top_level.txt
pysterior/spikes/__init__.py
pysterior/spikes/density_spikes.py
pysterior/spikes/functional_spikes.py
pysterior/spikes/theano_spikes.py
pysterior/tests/__init__.py
pysterior/tests/classification_tests.py
pysterior/tests/linear_regression_tests.py
pysterior/tests/polynomial.py