Metadata-Version: 1.1
Name: pysterior
Version: 0.1.5
Summary: Bayesian machine learning in Python.
Home-page: https://github.com/lmc2179/pysterior
Author: Louis Cialdella
Author-email: louiscialdella@gmail.com
License: MIT
Keywords: bayesian machine learning mcmc
Platform: UNKNOWN
Classifier: Development Status :: 3 - Alpha
Classifier: Intended Audience :: Developers
Classifier: Topic :: Scientific/Engineering :: Artificial Intelligence
Classifier: Intended Audience :: Science/Research
Classifier: Topic :: Scientific/Engineering :: Information Analysis
Classifier: License :: OSI Approved :: MIT License
Classifier: Programming Language :: Python :: 3
Classifier: Programming Language :: Python :: 3.2
Classifier: Programming Language :: Python :: 3.3
Classifier: Programming Language :: Python :: 3.4
